{
  "version": "0.1.0",
  "entities": [
    {
      "id": 4,
      "name": "Area4",
      "kind": {
        "area": {
          "area_id": 1,
          "rect": {
            "x": 8.32e2,
            "y": 1.76e2,
            "width": 1.6e1,
            "height": -1.6e1
          }
        }
      }
    },
    {
      "id": 11,
      "name": "Contour11",
      "kind": {
        "contour": {
          "contour_id": 5,
          "points": [
            {
              "x": 2.4e2,
              "y": 1.76e2
            },
            {
              "x": 2.4e2,
              "y": 3.52e2
            },
            {
              "x": 3.04e2,
              "y": 2.56e2
            }
          ]
        }
      }
    },
    {
      "id": 12,
      "name": "Area12",
      "kind": {
        "area": {
          "area_id": 0,
          "rect": {
            "x": 3.52e2,
            "y": 2.08e2,
            "width": 2.56e2,
            "height": 1.76e2
          }
        }
      }
    },
    {
      "id": 13,
      "name": "Spawner13",
      "kind": {
        "spawner": {
          "spawner_id": 3,
          "points": [
            {
              "x": 1.28e2,
              "y": 5.44e2
            },
            {
              "x": 1.12e2,
              "y": 3.84e2
            }
          ]
        }
      }
    }
  ],
  "next_id": 14,
  "next_contour_id": 6,
  "next_spawner_id": 4
}